soiltexture/FAO.dat
soiltexture/INTERNATIONAL.dat
soiltexture/ISSS.dat
soiltexture/USDA.dat
soiltexture/__init__.py
soiltexture/texture.py
soiltexture-1.0.4.dist-info/LICENSE
soiltexture-1.0.4.dist-info/METADATA
soiltexture-1.0.4.dist-info/WHEEL
soiltexture-1.0.4.dist-info/top_level.txt
soiltexture-1.0.4.dist-info/RECORD
