Metadata-Version: 2.1
Name: soiltexture
Version: 1.0.4
Summary: Soil texture classification
Home-page: https://github.com/sagitta1618/soiltexture
Author: sagitta1618
License: UNKNOWN
Platform: UNKNOWN
Classifier: Programming Language :: Python :: 3
Classifier: License :: OSI Approved :: GNU General Public License v3 (GPLv3)
Classifier: Operating System :: OS Independent
